Metadata-Version: 2.4
Name: hack4uCourses
Version: 0.1.0
Summary: Una biblioteca para consultar cursos de Hack4u
Home-page: https://hack4u.io
Author: Luka Tinarelli
Dynamic: author
Dynamic: description
Dynamic: description-content-type
Dynamic: home-page
Dynamic: summary
